{
  "_class": "group",
  "do_objectID": "1B4F2225-44E1-4009-B9C7-728ED94752C6",
  "exportOptions": {
    "_class": "exportOptions",
    "exportFormats": [
    ],
    "includedLayerIds": [
    ],
    "layerOptions": 0,
    "shouldTrim": false
  },
  "frame": {
    "_class": "rect",
    "constrainProportions": false,
    "height": 37,
    "width": 86,
    "x": 1169,
    "y": 3471
  },
  "hasClickThrough": false,
  "isFlippedHorizontal": false,
  "isFlippedVertical": false,
  "isLocked": false,
  "isVisible": true,
  "layerListExpandedType": 0,
  "layers": [
    {
      "class": "shapeGroup",
      "id": "3466CFAF-A7E9-4960-8955-2F525DE851FE"
    },
    {
      "class": "text",
      "id": "540CB450-41B9-481F-9AE4-FF2C7D778F37"
    }
  ],
  "name": "nextBtn",
  "nameIsFixed": true,
  "resizingConstraint": 63,
  "resizingType": 0,
  "rotation": 0,
  "shouldBreakMaskChain": false,
  "style": {
    "_class": "style",
    "endDecorationType": 0,
    "miterLimit": 10,
    "startDecorationType": 0
  }
}